<xml xmlns="https://developers.google.com/blockly/xml"><variables><variable id="[dv^8E]V=U0EV5a;f^pH">l</variable><variable id="woHC^aO(-67gvNY~]6Va">time</variable></variables><block type="ctx_subscribe" id="1oBbsK715xK{-qeIIT[u" x="1477" y="-362"><field name="CTX_NAME">Lab</field><value name="NAME"><shadow type="text" id="q/f[TSu|=NwJ|IQ-e%IW"><field name="TEXT">Light During Emergency</field></shadow></value><value name="CTX_VAR_NAME"><block type="variables_get" id=",w^S,66Dc!.f}cn^0b26"><field name="VAR" id="[dv^8E]V=U0EV5a;f^pH">l</field></block></value><statement name="CONTENT"><block type="bp_basic_bsync" id="v0/_0~]a:7Cp.V9M@1Ay"><mutation xmlns="http://www.w3.org/1999/xhtml" block="1" interrupt="1"></mutation><value name="Block"><block type="ctx_update_db_new" id="|-`XTB:]xj:fVY/*RC3{"><field name="COMMAND">OpenLab</field><statement name="CONTENT"><block type="property_value" id="!0Se5CJ%Lsv!zEO@L!y,"><value name="PROPERTY"><shadow type="text" id="W(nb{dX+*;F8|shs^6;%"><field name="TEXT">lab</field></shadow></value><value name="VALUE"><block type="variables_get" id="L/9AWc)|I,/4VGQ1th55"><field name="VAR" id="[dv^8E]V=U0EV5a;f^pH">l</field></block></value></block></statement></block></value><value name="Interrupt"><block type="ctx_context_ended_data" id="kaDIMucrxxKOoW9./y=A"><field name="COMMAND">Lab</field><value name="DATA"><block type="variables_get" id="9a,c?o+aqD%Uy?zd#0OC"><field name="VAR" id="[dv^8E]V=U0EV5a;f^pH">l</field></block></value></block></value></block></statement></block><block type="ctx_subscribe" id="_B_hdgTsQ0.7mwH}r@X[" x="-264" y="-133"><field name="CTX_NAME">Lab</field><value name="NAME"><shadow type="text" id="6(=}0Vx|vyDWVp0r?{|g"><field name="TEXT">Turn on/off lab light when...</field></shadow></value><value name="CTX_VAR_NAME"><block type="variables_get" id="$|r[sICZ/jm`4{5^o~J["><field name="VAR" id="[dv^8E]V=U0EV5a;f^pH">l</field></block></value><statement name="CONTENT"><block type="bp_basic_bsync" id="LE`fzfZN3Bc=}a;gmkNw"><mutation xmlns="http://www.w3.org/1999/xhtml" wait="1" request="1"></mutation><value name="Wait"><block type="ctx_update_db_new" id="}@j-_^K5tsP+]iN#5sz_"><field name="COMMAND">OpenLab</field><statement name="CONTENT"><block type="property_value" id="H^r}$fUzGG[In~2-iT*f"><value name="PROPERTY"><shadow type="text" id="d)2x].f@}+6A`$#i%YE+"><field name="TEXT">sensor</field></shadow></value><value name="VALUE"><block type="get_object_value" id="|N4,#q$gi}w[#b5IA@KW"><value name="OBJECT"><block type="variables_get" id="vjlzniddo/h~3V*woKS/"><field name="VAR" id="[dv^8E]V=U0EV5a;f^pH">l</field></block></value><value name="PROPERTY"><shadow type="text" id="rJv(]Ub%F~`,aj}5C.=g"><field name="TEXT">motionSensor</field></shadow></value></block></value></block></statement></block></value><value name="Request"><block type="ctx_update_db_new" id=";gy`NrU:vEa-7p^IDquK"><field name="COMMAND">OpenLab</field><statement name="CONTENT"><block type="property_value" id="WfATq;psQBqd+MRki)mP"><value name="PROPERTY"><shadow type="text" id=";Iqxl(,Co?].#Z8{}LzI"><field name="TEXT">lab</field></shadow></value><value name="VALUE"><block type="variables_get" id="0ab?_serVjgea]1-bInE"><field name="VAR" id="[dv^8E]V=U0EV5a;f^pH">l</field></block></value></block></statement></block></value><next><block type="bp_basic_bsync" id="U:|GB7M*k7,`I3(IlUoD"><mutation xmlns="http://www.w3.org/1999/xhtml" wait="1" request="1"></mutation><value name="Wait"><block type="ctx_update_db_new" id="SnuSbuFI+9B-EE;J1GC3"><field name="COMMAND">OpenLab</field><statement name="CONTENT"><block type="property_value" id="eo8lYI#@N[-!n?=8rpZR"><value name="PROPERTY"><shadow type="text" id="mlzZR5w|k8:T4=z`a;E/"><field name="TEXT">sensor</field></shadow></value><value name="VALUE"><block type="get_object_value" id="K`c.qmCQ=-=`GKu[`}a!"><value name="OBJECT"><block type="variables_get" id="b_LQxs(eDSOf1QS(Ywfz"><field name="VAR" id="[dv^8E]V=U0EV5a;f^pH">l</field></block></value><value name="PROPERTY"><shadow type="text" id="E2^gGC;$/-pC)g@q2~1D"><field name="TEXT">motionSensor</field></shadow></value></block></value></block></statement></block></value><value name="Request"><block type="ctx_update_db_new" id="e7BSX-]A:1!=.Wq`U+^Y"><field name="COMMAND">OpenLab</field><statement name="CONTENT"><block type="property_value" id="u!svQLyHpm4^,RkA[FFn"><value name="PROPERTY"><shadow type="text" id="0`/jWoz=;v6!)uy?bqa7"><field name="TEXT">lab</field></shadow></value><value name="VALUE"><block type="variables_get" id="tOiFy6Lmzj[d8QQEN$jq"><field name="VAR" id="[dv^8E]V=U0EV5a;f^pH">l</field></block></value></block></statement></block></value></block></next></block></statement></block><block type="ctx_subscribe" id="%|g,d*#9Kp!J^KwKBZHJ" x="631" y="-106"><field name="CTX_NAME">Lab</field><value name="NAME"><shadow type="text" id="VcWtP)elp!sjti-0PM[p"><field name="TEXT">Turn on/off lab light when...</field></shadow></value><value name="CTX_VAR_NAME"><block type="variables_get" id="OP^d?Z2c3vm_n_%`z_Nb"><field name="VAR" id="[dv^8E]V=U0EV5a;f^pH">l</field></block></value><statement name="CONTENT"><block type="bp_basic_bsync" id="vL-7EmLfHzqg[gGpW+{0"><mutation xmlns="http://www.w3.org/1999/xhtml" wait="1" request="1"></mutation><value name="Wait"><block type="ctx_update_db_new" id="r1G0hlhj4HIs9}R29kbY"><field name="COMMAND">OpenLab</field><statement name="CONTENT"><block type="property_value" id="zsZvLX{@n]]}8-bCD_Wl"><value name="PROPERTY"><shadow type="text" id="^a,FC2f8d?%!qy(%wpr_"><field name="TEXT">sensor</field></shadow></value><value name="VALUE"><block type="get_object_value" id="bL}_PQ,hAiAm[?Y0RiFa"><value name="OBJECT"><block type="variables_get" id="^28,1;vKyA2D;^BU6?8S"><field name="VAR" id="[dv^8E]V=U0EV5a;f^pH">l</field></block></value><value name="PROPERTY"><shadow type="text" id="ehg|U}z8n~@.UMu;+08x"><field name="TEXT">motionSensor</field></shadow></value></block></value></block></statement></block></value><value name="Request"><block type="ctx_update_db_new" id="Ur@o!MKF)$F-vGLvSgV%"><field name="COMMAND">OpenLab</field><statement name="CONTENT"><block type="property_value" id="TCcI;d[T[G*0i2kjc9vl"><value name="PROPERTY"><shadow type="text" id="ocnIM]?8C_9?[Gd67E/l"><field name="TEXT">lab</field></shadow></value><value name="VALUE"><block type="variables_get" id="=y3.1S3fW;kEc5;62N_}"><field name="VAR" id="[dv^8E]V=U0EV5a;f^pH">l</field></block></value></block></statement></block></value><next><block type="bp_basic_bsync" id="h0e_@Mgx|Ea8JYVf!%-3"><mutation xmlns="http://www.w3.org/1999/xhtml" wait="1" request="1"></mutation><value name="Wait"><block type="ctx_update_db_new" id="DE]yR|+9J|L_X)VXBV;{"><field name="COMMAND">OpenLab</field><statement name="CONTENT"><block type="property_value" id="rjxdo3@.s9%c)gq0KX3G"><value name="PROPERTY"><shadow type="text" id="lSS~Z6RL9c!/:vS!H8fd"><field name="TEXT">sensor</field></shadow></value><value name="VALUE"><block type="get_object_value" id="?EbcoEtOe5Sv.EOYf:1@"><value name="OBJECT"><block type="variables_get" id="?Smh1G,c+8;OAQU)FZO."><field name="VAR" id="[dv^8E]V=U0EV5a;f^pH">l</field></block></value><value name="PROPERTY"><shadow type="text" id="Cmv-m|A?n$=FlP%j)QC,"><field name="TEXT">motionSensor</field></shadow></value></block></value></block></statement></block></value><value name="Request"><block type="ctx_update_db_new" id="*bQyhdcZT(MVIMkT::$t"><field name="COMMAND">OpenLab</field><statement name="CONTENT"><block type="property_value" id="h=A6|hoNTRr[lxA_I]^="><value name="PROPERTY"><shadow type="text" id="~-Hmk]rl(2cU*Jx+]YT|"><field name="TEXT">lab</field></shadow></value><value name="VALUE"><block type="variables_get" id="sO4CY#*h:RsQ1UD%dL%n"><field name="VAR" id="[dv^8E]V=U0EV5a;f^pH">l</field></block></value></block></statement></block></value></block></next></block></statement></block><block type="ctx_subscribe" id="=,Ahq42Ax}v[Wz/E5HcT" x="1478" y="-132"><field name="CTX_NAME">NonEmptyLab</field><value name="NAME"><shadow type="text" id="=p-[@;iS(~RjMl@!rxxz"><field name="TEXT">Turn on light for nonempty labs</field></shadow></value><value name="CTX_VAR_NAME"><block type="variables_get" id="~u$k{$XxaeNd~:1GWgO+"><field name="VAR" id="[dv^8E]V=U0EV5a;f^pH">l</field></block></value><statement name="CONTENT"><block type="bp_basic_bsync" id="AIcL9ZnTRaEft$*H1Kx6"><mutation xmlns="http://www.w3.org/1999/xhtml" request="1"></mutation><value name="Request"><block type="bp_event_with_data" id="V]vre;4r+u.^f92Qf=0G"><value name="NAME"><shadow type="text" id="+WXX9i(*X.lu0-v.C_a0"><field name="TEXT">turn lab's light on</field></shadow></value><value name="DATA"><block type="get_object_value" id="Y/Cs~[,jZM~z)3e=v2cp"><value name="OBJECT"><block type="variables_get" id="yrwqn^ht!:}e!(:qV,-@"><field name="VAR" id="[dv^8E]V=U0EV5a;f^pH">l</field></block></value><value name="PROPERTY"><shadow type="text" id="0Z=+HfM+q3g)De@XjoRY"><field name="TEXT">light</field></shadow></value></block></value></block></value></block></statement></block><block type="ctx_subscribe" id="hQAl~ZYKogH@[|j|jxEW" x="1479" y="47"><field name="CTX_NAME">EmptyLab</field><value name="NAME"><shadow type="text" id="}UffKV,cH;;8qQ[}k:Mi"><field name="TEXT">Turn off light for empty labs</field></shadow></value><value name="CTX_VAR_NAME"><block type="variables_get" id="NfD^ydx}kH6i{cB604v2"><field name="VAR" id="[dv^8E]V=U0EV5a;f^pH">l</field></block></value><statement name="CONTENT"><block type="bp_basic_bsync" id="o^@o%HlY%bF/7I,OetJg"><mutation xmlns="http://www.w3.org/1999/xhtml" request="1"></mutation><value name="Request"><block type="bp_event_with_data" id="Q})N+%)kU9+th+0Hu[mt"><value name="NAME"><shadow type="text" id="(gGV}]7vMVqDb}UTsa1T"><field name="TEXT">turn lab's light off</field></shadow></value><value name="DATA"><block type="get_object_value" id="-0}K;,iVX!g=#kUJZ1DW"><value name="OBJECT"><block type="variables_get" id="U+1nu1$$~1}8Zv3FWfJK"><field name="VAR" id="[dv^8E]V=U0EV5a;f^pH">l</field></block></value><value name="PROPERTY"><shadow type="text" id="r1^jmh.-NwD;)%r?0/ou"><field name="TEXT">light</field></shadow></value></block></value></block></value></block></statement></block><block type="ctx_subscribe" id="`E0(t9xd~YH[Tp,xL7de" x="1560" y="246"><field name="CTX_NAME">Lab</field><value name="NAME"><shadow type="text" id="`_+F]#*v:PulK#y+nQo^"><field name="TEXT">non empty/empty lab - motion sensor</field></shadow></value><value name="CTX_VAR_NAME"><block type="variables_get" id="13APN2YvgkX`ZLR^F@B6"><field name="VAR" id="[dv^8E]V=U0EV5a;f^pH">l</field></block></value><statement name="CONTENT"><block type="bp_basic_bsync" id="#/j=vLC~:6T**UC(A;b5"><mutation xmlns="http://www.w3.org/1999/xhtml" wait="1" request="1"></mutation><value name="Wait"><block type="ctx_update_db_new" id="?Aoj9%!`c;T)KJz=aZu;"><field name="COMMAND">OpenLab</field><statement name="CONTENT"><block type="property_value" id="8G33mEInFjD1yxXixKJ$"><value name="PROPERTY"><shadow type="text" id=".I^/5KhW#PwUE2-1nP-."><field name="TEXT">sensor</field></shadow></value><value name="VALUE"><block type="get_object_value" id="ILBF6B`oNDm|q11tK?nm"><value name="OBJECT"><block type="variables_get" id="3;UC^4dr0?[+HC/^kTbS"><field name="VAR" id="[dv^8E]V=U0EV5a;f^pH">l</field></block></value><value name="PROPERTY"><shadow type="text" id="HL83caV4Bd8/3JoBQu96"><field name="TEXT">motionSensor</field></shadow></value></block></value></block></statement></block></value><value name="Request"><block type="ctx_update_db_new" id="nB]dc2W~yh8Z{sj8o`M|"><field name="COMMAND">OpenLab</field><statement name="CONTENT"><block type="property_value" id="~qLuEG^;/`cT,wEj4w?N"><value name="PROPERTY"><shadow type="text" id="0;EUdZ+hq*,qnR!^Qbv!"><field name="TEXT">lab</field></shadow></value><value name="VALUE"><block type="variables_get" id="w0YEU@g^]CM=u?w{Z]9%"><field name="VAR" id="[dv^8E]V=U0EV5a;f^pH">l</field></block></value></block></statement></block></value><next><block type="bp_basic_bsync" id="E{KbN$f}8#=)vNt1#+n3"><mutation xmlns="http://www.w3.org/1999/xhtml" wait="1" request="1"></mutation><value name="Wait"><block type="ctx_update_db_new" id="pJ(-}ONu[f(i;Doy$n]R"><field name="COMMAND">OpenLab</field><statement name="CONTENT"><block type="property_value" id="~5ACTaU$]q%r8luFE21}"><value name="PROPERTY"><shadow type="text" id="L%Ox0mk7cXO$XTq9*cCJ"><field name="TEXT">sensor</field></shadow></value><value name="VALUE"><block type="get_object_value" id="!7BllpYK`rPK[St*JV#v"><value name="OBJECT"><block type="variables_get" id=",JpybZ+=Vngb2{o};Qxe"><field name="VAR" id="[dv^8E]V=U0EV5a;f^pH">l</field></block></value><value name="PROPERTY"><shadow type="text" id="BGIIRnx{BNDVg55vGI%7"><field name="TEXT">motionSensor</field></shadow></value></block></value></block></statement></block></value><value name="Request"><block type="ctx_update_db_new" id="~q0Yy(BzqGl}V4*Uikkb"><field name="COMMAND">OpenLab</field><statement name="CONTENT"><block type="property_value" id="z6(|dM:wl!b?dunO$g,7"><value name="PROPERTY"><shadow type="text" id="F@)b9FOZAdjg31M)}_ff"><field name="TEXT">lab</field></shadow></value><value name="VALUE"><block type="variables_get" id="40W3:{bWLtf%Q=Z#xrv/"><field name="VAR" id="[dv^8E]V=U0EV5a;f^pH">l</field></block></value></block></statement></block></value></block></next></block></statement></block><block type="ctx_subscribe" id="lh_/lY{MlC(T/)kW$=5%" x="-267" y="364"><field name="CTX_NAME">Lab</field><value name="NAME"><shadow type="text" id="lzQ_1}Cv,QW(-e*Yj}.7"><field name="TEXT">Turn on/off lab light based...</field></shadow></value><value name="CTX_VAR_NAME"><block type="variables_get" id="6nd/Ksgk)3RfZ?;|K5VJ"><field name="VAR" id="[dv^8E]V=U0EV5a;f^pH">l</field></block></value><statement name="CONTENT"><block type="bp_basic_bsync" id="Q(/I+}Njk80E#XMpy;}X"><mutation xmlns="http://www.w3.org/1999/xhtml" wait="1"></mutation><value name="Wait"><block type="bp_event_with_data" id="~yKuz{2~`Fiv#*O:lk/e"><value name="NAME"><shadow type="text" id="+Pob^Y`26=WcJbt}i5vC"><field name="TEXT">detected motion in the lab</field></shadow></value><value name="DATA"><block type="get_object_value" id=";.Fd2rU0M}U.cf4}%Io_"><value name="OBJECT"><block type="variables_get" id="oMIRturfe~]fPE*-0TEf"><field name="VAR" id="[dv^8E]V=U0EV5a;f^pH">l</field></block></value><value name="PROPERTY"><shadow type="text" id="LQ41JM,(7Eh)V8sKq:w|"><field name="TEXT">motionSensor</field></shadow></value></block></value></block></value><next><block type="bp_basic_bsync" id=")_#RWudz4FN.nTKO2y90"><mutation xmlns="http://www.w3.org/1999/xhtml" request="1"></mutation><value name="Request"><block type="bp_event_with_data" id="NJ4*}!E=9Y._[XeS`CKx"><value name="NAME"><shadow type="text" id="^SM#=`!j%r2Ay)yJDowB"><field name="TEXT">turn lab's light on</field></shadow></value><value name="DATA"><block type="get_object_value" id="|r/Obx3A_dDLQiu+g/#)"><value name="OBJECT"><block type="variables_get" id="=8P/,nEcg7J8;FP|Ui=."><field name="VAR" id="[dv^8E]V=U0EV5a;f^pH">l</field></block></value><value name="PROPERTY"><shadow type="text" id="!QWR,/cO:XD~OUZ!h2,["><field name="TEXT">light</field></shadow></value></block></value></block></value><next><block type="bp_basic_bsync" id="sH9Eyx+[1@i0J9aX@KRc"><mutation xmlns="http://www.w3.org/1999/xhtml" wait="1"></mutation><value name="Wait"><block type="bp_event_with_data" id="5Juaz|AY;INrO{qX@sFc"><value name="NAME"><shadow type="text" id="Dq1FXd7S!MlTik)9+bub"><field name="TEXT">motion stopped</field></shadow></value><value name="DATA"><block type="get_object_value" id="f._yXWN+,12O%NCA]z8V"><value name="OBJECT"><block type="variables_get" id="dVi|V~dOrx}(=Z8l8i?i"><field name="VAR" id="[dv^8E]V=U0EV5a;f^pH">l</field></block></value><value name="PROPERTY"><shadow type="text" id="w:9~w.e6RG|k#:)0$GqS"><field name="TEXT">motionSensor</field></shadow></value></block></value></block></value><next><block type="bp_basic_bsync" id="w@lN6K]*2OOL8@+;Y)tO"><mutation xmlns="http://www.w3.org/1999/xhtml" request="1"></mutation><value name="Request"><block type="bp_event_with_data" id="9ru87vCT`!6YbZL+dm1t"><value name="NAME"><shadow type="text" id="N]`s*E2*VU@@1;qW-UTw"><field name="TEXT">turn lab's light off</field></shadow></value><value name="DATA"><block type="get_object_value" id=")q8ZG/bvu|Dq,cS[:1V9"><value name="OBJECT"><block type="variables_get" id="L||[x)`(pvdC5bhWcu4X"><field name="VAR" id="[dv^8E]V=U0EV5a;f^pH">l</field></block></value><value name="PROPERTY"><shadow type="text" id="alI$Rh]k|lCwF~cYBPY_"><field name="TEXT">light</field></shadow></value></block></value></block></value></block></next></block></next></block></next></block></statement></block><block type="bp_register_bthread" id="-.g9ih+_m~G/Dh{Cn*`g" x="619" y="364"><value name="NAME"><shadow type="text" id="h*9_Nc$:0Nz#$+5*L2;j"><field name="TEXT">Turn off lab light when motion stopped</field></shadow></value><statement name="CONTENT"><block type="bp_basic_bsync" id="j{ag=530_-x4~,$_ca3v"><mutation xmlns="http://www.w3.org/1999/xhtml" wait="1"></mutation><value name="Wait"><block type="bp_event" id="n.6%XQAl4h%G0QV$Xn#E"><value name="NAME"><shadow type="text" id="4~lLDdCkz{/NHbw26+1O"><field name="TEXT">motion stopped</field></shadow></value></block></value><next><block type="variables_set" id=";j3!UXz@Y,VYgi11GcST"><field name="VAR" id="woHC^aO(-67gvNY~]6Va">time</field><value name="VALUE"><block type="procedures_callreturn" id="Q+[UeKSJ=^$Y71vp6Ceq"><mutation name="Clock.time"/></block></value><next><block type="bp_basic_bsync" id="-pOIlMl:8C2~g-g_K[@w"><mutation xmlns="http://www.w3.org/1999/xhtml" wait="1" block="1"></mutation><value name="Wait"><block type="logic_compare" id="qRp6[Y6hUm{Jn@,zj=nm"><field name="OP">GTE</field><value name="A"><block type="procedures_callreturn" id="DLcL=nxfGdzgVIFh}K.8"><mutation name="Clock.time"/></block></value><value name="B"><block type="math_arithmetic" id="xKMdYt4+F`-8HOq=F-EA"><field name="OP">ADD</field><value name="A"><shadow type="math_number" id="RAG`#r#2a-+RqLu_66AL"><field name="NUM">1</field></shadow><block type="variables_get" id="m!pp|4vC#4oBhR)KGURB"><field name="VAR" id="woHC^aO(-67gvNY~]6Va">time</field></block></value><value name="B"><shadow type="math_number" id="%btz:@{f*6xM4{z66+EF"><field name="NUM">180000</field></shadow></value></block></value></block></value><value name="Block"><block type="bp_event" id="+.NR}`9YT`-2Wv*wsd?T"><value name="NAME"><shadow type="text" id="ww9tRJ6Mo4%OD?Y7wz[."><field name="TEXT">turn lab light off</field></shadow></value></block></value></block></next></block></next></block></statement></block><block type="bp_register_bthread" id="eqj]8}_vO?XFFu1|-M1_" x="442" y="740"><value name="NAME"><shadow type="text" id="NFX9A(kdldQ0H;0m#`du"><field name="TEXT">Turn lights on/off based on motion detection</field></shadow></value><statement name="CONTENT"><block type="bp_basic_bsync" id="=%FM,g?n@Zb#n8*dcUT{"><mutation xmlns="http://www.w3.org/1999/xhtml" wait="1"></mutation><value name="Wait"><block type="bp_event" id="b)Zcc:%mP1S[)COW*y4v"><value name="NAME"><shadow type="text" id="h[o8g**:i1,6)/Gr;g;j"><field name="TEXT">detected motion in the lab</field></shadow></value></block></value><next><block type="bp_basic_bsync" id="2Q9+u2,X~[P,9sWC|,l0"><mutation xmlns="http://www.w3.org/1999/xhtml" request="1"></mutation><value name="Request"><block type="bp_event" id="jUt`6yp.7,`aesO;4^vS"><value name="NAME"><shadow type="text" id="8i*y_3:s3rEcIPb:)aUR"><field name="TEXT">turn lab's light on</field></shadow></value></block></value><next><block type="bp_basic_bsync" id="5uuFlO-eVPUUCDlg_CRW"><mutation xmlns="http://www.w3.org/1999/xhtml" wait="1"></mutation><value name="Wait"><block type="bp_event" id="/%ZjDh|n8e{z(:6cWnma"><value name="NAME"><shadow type="text" id="%Q0xcF|[Ti(SrYUWcO]9"><field name="TEXT">motion stopped</field></shadow></value></block></value><next><block type="bp_basic_bsync" id="+Q0CKc`Tp[SQhGDuai6D"><mutation xmlns="http://www.w3.org/1999/xhtml" request="1"></mutation><value name="Request"><block type="bp_event" id="PvZ.Gwnzhi@vsscBsIQz"><value name="NAME"><shadow type="text" id="rN2=-rJ0y@[^T.mXaciO"><field name="TEXT">turn lab's light off</field></shadow></value></block></value></block></next></block></next></block></next></block></statement></block><block type="ctx_subscribe" id="?iN55]EJj,`~,[TtsQUA" x="-244" y="791"><field name="CTX_NAME">Lab</field><value name="NAME"><shadow type="text" id="qV^pXQG%8+(n8;*[F({8"><field name="TEXT">Turn on/off lab light based...</field></shadow></value><value name="CTX_VAR_NAME"><block type="variables_get" id="USEBQYwMm.9Yh[01t%}("><field name="VAR" id="[dv^8E]V=U0EV5a;f^pH">l</field></block></value><statement name="CONTENT"><block type="bp_basic_bsync" id="`itkY[9BYB^jc,HdA[SF"><mutation xmlns="http://www.w3.org/1999/xhtml" wait="1"></mutation><value name="Wait"><block type="bp_event_with_data" id=";mPb{%/Xo3qZfX;7OH/-"><value name="NAME"><shadow type="text" id="p/qUT2`^HtIYLIbb9gNz"><field name="TEXT">detected motion in the lab</field></shadow></value><value name="DATA"><block type="object" id="je2rh[ssmi(D(ICn#qR;"><statement name="LIST"><block type="property_value" id="pqZ.=/,Xm=Q5oZgz(2,/"><value name="PROPERTY"><shadow type="text" id="tO8RUfQaSQ,L|vV^iR3f"><field name="TEXT">lab</field></shadow></value><value name="VALUE"><block type="variables_get" id="U5e_67R7^V71tAX/Dtk."><field name="VAR" id="[dv^8E]V=U0EV5a;f^pH">l</field></block></value></block></statement></block></value></block></value><next><block type="bp_basic_bsync" id="unxNZtCGqA3U;}8y@J+q"><mutation xmlns="http://www.w3.org/1999/xhtml" request="1"></mutation><value name="Request"><block type="bp_event_with_data" id="/*PoZ2q#lso|v_`1F,Mb"><value name="NAME"><shadow type="text" id="|X_LxyCh*yzOYLLVEXzL"><field name="TEXT">turn lab's light on</field></shadow></value><value name="DATA"><block type="object" id="AiRlh|Td,rcVC9-Qs^3Q"><statement name="LIST"><block type="property_value" id="K:ktGo=KtKxxqcjh,Q}%"><value name="PROPERTY"><shadow type="text" id="NkLk8b1H#aaU|wlSPTQ|"><field name="TEXT">lab</field></shadow></value><value name="VALUE"><block type="variables_get" id="oYl;pq0}nCZ{[_M]Xc_="><field name="VAR" id="[dv^8E]V=U0EV5a;f^pH">l</field></block></value></block></statement></block></value></block></value><next><block type="bp_basic_bsync" id="ln9lt$rY}OldFlEr/~W)"><mutation xmlns="http://www.w3.org/1999/xhtml" wait="1"></mutation><value name="Wait"><block type="bp_event_with_data" id="m6m@F]1n!9qG7r-kwg5r"><value name="NAME"><shadow type="text" id="d*gE8Ty,g`9FS;Z,GZ`="><field name="TEXT">motion stopped</field></shadow></value><value name="DATA"><block type="object" id="u475fq47bc9#eRJe-%.k"><statement name="LIST"><block type="property_value" id="i4(UMb7+pb-U}=M{Ll:9"><value name="PROPERTY"><shadow type="text" id="zAm?jy[E-N$]SomzR?Dk"><field name="TEXT">lab</field></shadow></value><value name="VALUE"><block type="variables_get" id="ci-nJqBnxZMKYLhz^P/:"><field name="VAR" id="[dv^8E]V=U0EV5a;f^pH">l</field></block></value></block></statement></block></value></block></value><next><block type="bp_basic_bsync" id="]I|$h94%TIA6KiXWz.x{"><mutation xmlns="http://www.w3.org/1999/xhtml" request="1"></mutation><value name="Request"><block type="bp_event_with_data" id="qGBYb6too9n*@Z_niDb:"><value name="NAME"><shadow type="text" id="!.5wuI;qc53.zXW7{o]@"><field name="TEXT">turn lab's light on</field></shadow></value><value name="DATA"><block type="object" id="H=0PX:oq%OfX@bNnHB+f"><statement name="LIST"><block type="property_value" id="].l?SVX9.6g-{+L5M02v"><value name="PROPERTY"><shadow type="text" id="Rz3ISXArE;qu7?,(x+d:"><field name="TEXT">lab</field></shadow></value><value name="VALUE"><block type="variables_get" id="kbQcA%j#PZ*1.~tU,H`+"><field name="VAR" id="[dv^8E]V=U0EV5a;f^pH">l</field></block></value></block></statement></block></value></block></value></block></next></block></next></block></next></block></statement></block><block type="bp_register_bthread" id="tED)hkuAOpq|`zZKJ$I2" x="996" y="989"><value name="NAME"><shadow type="text" id="em?{xQIcXcH!-a`Zj=Np"><field name="TEXT">Turn on lab light when detected motion in the lab</field></shadow></value><statement name="CONTENT"><block type="bp_basic_bsync" id="@%nwz=4yk,2iKoK9irB="><mutation xmlns="http://www.w3.org/1999/xhtml" wait="1" request="1"></mutation><value name="Wait"><block type="bp_event" id="-ruO-G{f?9wpg+8$G8G8"><value name="NAME"><shadow type="text" id="]1qhEJh8zdJh/L`tOgfL"><field name="TEXT">detected motion in the lab</field></shadow></value></block></value><value name="Request"><block type="bp_event" id="8!%;Hb:vs9H*AiOfVQ9g"><value name="NAME"><shadow type="text" id="q6hPQkebH9AaT{tv5bq}"><field name="TEXT">turn lab light on</field></shadow></value></block></value><next><block type="bp_basic_bsync" id="l,AE{v8:lvUd,b`F{VUq"><mutation xmlns="http://www.w3.org/1999/xhtml" wait="1" request="1"></mutation><value name="Wait"><block type="bp_event" id="rTKN/%L(iaeA2df}h!mC"><value name="NAME"><shadow type="text" id="IFx3Nvx~:dRC(.0Fxbmg"><field name="TEXT">motion stopped</field></shadow></value></block></value><value name="Request"><block type="bp_event" id="?SvnpC7%=v,@Gn;/i+/p"><value name="NAME"><shadow type="text" id="OR`-iYw1*RyT|}JFe@Zq"><field name="TEXT">turn lab light off</field></shadow></value></block></value></block></next></block></statement></block><block type="procedures_defreturn" id="s/y1}UbPISg?trd5qJ)^" x="525" y="1044"><field name="NAME">Clock.time</field><comment pinned="false" h="80" w="160">Describe this function...</comment></block><block type="ctx_subscribe" id="1F^xuMFqU;%F@pv3V%3m" x="442" y="1273"><field name="CTX_NAME">Lab</field><value name="NAME"><shadow type="text" id="tyVzG-47$=#Mp/pSoS/W"><field name="TEXT">Lights During Emergency</field></shadow></value><value name="CTX_VAR_NAME"><block type="variables_get" id="8CeK_uudnogN$-0I{NK)"><field name="VAR" id="[dv^8E]V=U0EV5a;f^pH">l</field></block></value><statement name="CONTENT"><block type="bp_basic_bsync" id="RJf8H,)O=Xrj^5#e5`hh"><mutation xmlns="http://www.w3.org/1999/xhtml" block="1"></mutation><value name="Block"><block type="bp_event_with_data" id="=/8UuJ}ezqIv[O/%UTiH"><value name="NAME"><shadow type="text" id="!|@ekjE0cEDm~.nkl6Sn"><field name="TEXT">turn lab light off</field></shadow></value><value name="DATA"><block type="object" id="J9E7=^lOYk3z:_E5ON.1"><statement name="LIST"><block type="property_value" id="^%]1rzZm/Hnt|A3$g#1_"><value name="PROPERTY"><shadow type="text" id="DI2Jd|LV3m9,h92S)TiB"><field name="TEXT">lab</field></shadow></value><value name="VALUE"><block type="variables_get" id="WfhfcQvLMKyD0}1HCsV_"><field name="VAR" id="[dv^8E]V=U0EV5a;f^pH">l</field></block></value></block></statement></block></value></block></value></block></statement></block></xml>